score/doc/__init__.py
score.doc-0.1.dist-info/DESCRIPTION.rst
score.doc-0.1.dist-info/METADATA
score.doc-0.1.dist-info/RECORD
score.doc-0.1.dist-info/WHEEL
score.doc-0.1.dist-info/entry_points.txt
score.doc-0.1.dist-info/metadata.json
score.doc-0.1.dist-info/top_level.txt
